<?xml version="1.0" standalone="yes"?>  <DATAPACKET Version="2.0"><METADATA><FIELDS><FIELD attrname="ID_FC" fieldtype="i4" required="true"><PARAM Name="PROVFLAGS" Value="7" Type="i4" Roundtrip="True"/><PARAM Name="ORIGIN" Value="ID_FC" Roundtrip="True"/></FIELD><FIELD attrname="TIPOCPBTE" fieldtype="string" required="true" WIDTH="2"><PARAM Name="ORIGIN" Value="TIPOCPBTE" Roundtrip="True"/></FIELD><FIELD attrname="CLASECPBTE" fieldtype="string" required="true" WIDTH="2"><PARAM Name="ORIGIN" Value="CLASECPBTE" Roundtrip="True"/></FIELD><FIELD attrname="CODIGO" fieldtype="string" required="true" WIDTH="6"><PARAM Name="ORIGIN" Value="CODIGO" Roundtrip="True"/></FIELD><FIELD attrname="NROCPBTE" fieldtype="string" WIDTH="13"><PARAM Name="ORIGIN" Value="NROCPBTE" Roundtrip="True"/></FIELD><FIELD attrname="LETRAFAC" fieldtype="string" required="true" SUBTYPE="FixedChar" WIDTH="1"><PARAM Name="ORIGIN" Value="LETRAFAC" Roundtrip="True"/></FIELD><FIELD attrname="SUCFAC" fieldtype="string" WIDTH="4"><PARAM Name="ORIGIN" Value="SUCFAC" Roundtrip="True"/></FIELD><FIELD attrname="NUMEROFAC" fieldtype="string" WIDTH="8"><PARAM Name="ORIGIN" Value="NUMEROFAC" Roundtrip="True"/></FIELD><FIELD attrname="NOMBRE" fieldtype="string" WIDTH="35"><PARAM Name="ORIGIN" Value="NOMBRE" Roundtrip="True"/></FIELD><FIELD attrname="RAZONSOCIAL" fieldtype="string" WIDTH="35"><PARAM Name="ORIGIN" Value="RAZONSOCIAL" Roundtrip="True"/></FIELD><FIELD attrname="DIRECCION" fieldtype="string" WIDTH="35"><PARAM Name="ORIGIN" Value="DIRECCION" Roundtrip="True"/></FIELD><FIELD attrname="CPOSTAL" fieldtype="string" WIDTH="8"><PARAM Name="ORIGIN" Value="CPOSTAL" Roundtrip="True"/></FIELD><FIELD attrname="LOCALIDAD" fieldtype="string" WIDTH="15"><PARAM Name="ORIGIN" Value="LOCALIDAD" Roundtrip="True"/></FIELD><FIELD attrname="TIPOIVA" fieldtype="i4" required="true"><PARAM Name="ORIGIN" Value="TIPOIVA" Roundtrip="True"/></FIELD><FIELD attrname="CUIT" fieldtype="string" WIDTH="13"><PARAM Name="ORIGIN" Value="CUIT" Roundtrip="True"/></FIELD><FIELD attrname="LISTAPRECIO" fieldtype="i4"><PARAM Name="ORIGIN" Value="LISTAPRECIO" Roundtrip="True"/></FIELD><FIELD attrname="FECHAVTA" fieldtype="SQLdateTime" required="true"><PARAM Name="ORIGIN" Value="FECHAVTA" Roundtrip="True"/></FIELD><FIELD attrname="FECHAVTO" fieldtype="SQLdateTime"><PARAM Name="ORIGIN" Value="FECHAVTO" Roundtrip="True"/></FIELD><FIELD attrname="FECHA_FISCAL" fieldtype="SQLdateTime"><PARAM Name="ORIGIN" Value="FECHA_FISCAL" Roundtrip="True"/></FIELD><FIELD attrname="CONDICIONVTA" fieldtype="i4" required="true"><PARAM Name="ORIGIN" Value="CONDICIONVTA" Roundtrip="True"/></FIELD><FIELD attrname="ANULADO" fieldtype="string" required="true" SUBTYPE="FixedChar" WIDTH="1"><PARAM Name="ORIGIN" Value="ANULADO" Roundtrip="True"/></FIELD><FIELD attrname="NRORTO" fieldtype="string" WIDTH="100"><PARAM Name="ORIGIN" Value="NRORTO" Roundtrip="True"/></FIELD><FIELD attrname="N_OPERACION2" fieldtype="r8"><PARAM Name="ORIGIN" Value="N_OPERACION2" Roundtrip="True"/></FIELD><FIELD attrname="NETOGRAV1" fieldtype="r8" required="true"><PARAM Name="ORIGIN" Value="NETOGRAV1" Roundtrip="True"/></FIELD><FIELD attrname="NETOGRAV2" fieldtype="r8" required="true"><PARAM Name="ORIGIN" Value="NETOGRAV2" Roundtrip="True"/></FIELD><FIELD attrname="NETONOGRAV1" fieldtype="r8" required="true"><PARAM Name="ORIGIN" Value="NETONOGRAV1" Roundtrip="True"/></FIELD><FIELD attrname="NETONOGRAV2" fieldtype="r8" required="true"><PARAM Name="ORIGIN" Value="NETONOGRAV2" Roundtrip="True"/></FIELD><FIELD attrname="DSTO" fieldtype="r8" required="true"><PARAM Name="ORIGIN" Value="DSTO" Roundtrip="True"/></FIELD><FIELD attrname="DSTOIMPORTE" fieldtype="r8" required="true"><PARAM Name="ORIGIN" Value="DSTOIMPORTE" Roundtrip="True"/></FIELD><FIELD attrname="NETOEXEN1" fieldtype="r8" required="true"><PARAM Name="ORIGIN" Value="NETOEXEN1" Roundtrip="True"/></FIELD><FIELD attrname="NETOEXEN2" fieldtype="r8" required="true"><PARAM Name="ORIGIN" Value="NETOEXEN2" Roundtrip="True"/></FIELD><FIELD attrname="TOTAL" fieldtype="r8" required="true"><PARAM Name="ORIGIN" Value="TOTAL" Roundtrip="True"/></FIELD><FIELD attrname="DEBE" fieldtype="r8" required="true"><PARAM Name="ORIGIN" Value="DEBE" Roundtrip="True"/></FIELD><FIELD attrname="IMPRESO" fieldtype="string" required="true" SUBTYPE="FixedChar" WIDTH="1"><PARAM Name="ORIGIN" Value="IMPRESO" Roundtrip="True"/></FIELD><FIELD attrname="OBSERVACION1" fieldtype="string" WIDTH="60"><PARAM Name="ORIGIN" Value="OBSERVACION1" Roundtrip="True"/></FIELD><FIELD attrname="OBSERVACION2" fieldtype="string" WIDTH="60"><PARAM Name="ORIGIN" Value="OBSERVACION2" Roundtrip="True"/></FIELD><FIELD attrname="CPTE_MANUAL" fieldtype="string" required="true" SUBTYPE="FixedChar" WIDTH="1"><PARAM Name="ORIGIN" Value="CPTE_MANUAL" Roundtrip="True"/></FIELD><FIELD attrname="SUCURSAL" fieldtype="i4" required="true"><PARAM Name="ORIGIN" Value="SUCURSAL" Roundtrip="True"/></FIELD><FIELD attrname="FACTURANRO" fieldtype="string" WIDTH="13"><PARAM Name="ORIGIN" Value="FACTURANRO" Roundtrip="True"/></FIELD><FIELD attrname="ZONA" fieldtype="i4"><PARAM Name="ORIGIN" Value="ZONA" Roundtrip="True"/></FIELD><FIELD attrname="LDR" fieldtype="i4" required="true"><PARAM Name="ORIGIN" Value="LDR" Roundtrip="True"/></FIELD><FIELD attrname="DEPOSITO" fieldtype="i4" required="true"><PARAM Name="ORIGIN" Value="DEPOSITO" Roundtrip="True"/></FIELD><FIELD attrname="CALCULA_SOBRETASA" fieldtype="string" required="true" SUBTYPE="FixedChar" WIDTH="1"><PARAM Name="ORIGIN" Value="CALCULA_SOBRETASA" Roundtrip="True"/></FIELD><FIELD attrname="DESGLOZAIVA" fieldtype="string" required="true" SUBTYPE="FixedChar" WIDTH="1"><PARAM Name="ORIGIN" Value="DESGLOZAIVA" Roundtrip="True"/></FIELD><FIELD attrname="NROENTREGA" fieldtype="i4"><PARAM Name="ORIGIN" Value="NROENTREGA" Roundtrip="True"/></FIELD><FIELD attrname="INGRESA_A_CTACTE" fieldtype="string" required="true" SUBTYPE="FixedChar" WIDTH="1"><PARAM Name="ORIGIN" Value="INGRESA_A_CTACTE" Roundtrip="True"/></FIELD><FIELD attrname="INGRESA_LIBRO_IVA" fieldtype="string" required="true" SUBTYPE="FixedChar" WIDTH="1"><PARAM Name="ORIGIN" Value="INGRESA_LIBRO_IVA" Roundtrip="True"/></FIELD><FIELD attrname="TIPO_REMITO" fieldtype="string" WIDTH="2"><PARAM Name="ORIGIN" Value="TIPO_REMITO" Roundtrip="True"/></FIELD><FIELD attrname="IDREMITO" fieldtype="i4"><PARAM Name="ORIGIN" Value="IDREMITO" Roundtrip="True"/></FIELD><FIELD attrname="REDUCIDA" fieldtype="string" SUBTYPE="FixedChar" WIDTH="1"><PARAM Name="ORIGIN" Value="REDUCIDA" Roundtrip="True"/></FIELD><FIELD attrname="COMSIONVENDEDOR" fieldtype="r8" required="true"><PARAM Name="ORIGIN" Value="COMSIONVENDEDOR" Roundtrip="True"/></FIELD><FIELD attrname="LIQUIDADA" fieldtype="string" SUBTYPE="FixedChar" WIDTH="1"><PARAM Name="ORIGIN" Value="LIQUIDADA" Roundtrip="True"/></FIELD><FIELD attrname="FECHA_LIQUIDACION" fieldtype="SQLdateTime"><PARAM Name="ORIGIN" Value="FECHA_LIQUIDACION" Roundtrip="True"/></FIELD><FIELD attrname="VENDEDOR" fieldtype="string" WIDTH="6"><PARAM Name="ORIGIN" Value="VENDEDOR" Roundtrip="True"/></FIELD><FIELD attrname="USUARIO" fieldtype="string" WIDTH="50"><PARAM Name="ORIGIN" Value="USUARIO" Roundtrip="True"/></FIELD><FIELD attrname="NC_CONTADO" fieldtype="string" SUBTYPE="FixedChar" WIDTH="1"><PARAM Name="ORIGIN" Value="NC_CONTADO" Roundtrip="True"/></FIELD><FIELD attrname="CAJA_POR_DEFECTO" fieldtype="i4"><PARAM Name="ORIGIN" Value="CAJA_POR_DEFECTO" Roundtrip="True"/></FIELD><FIELD attrname="NRO_Z" fieldtype="i4"><PARAM Name="ORIGIN" Value="NRO_Z" Roundtrip="True"/></FIELD><FIELD attrname="VALORES_RECIBIDOS" fieldtype="r8" required="true"><PARAM Name="ORIGIN" Value="VALORES_RECIBIDOS" Roundtrip="True"/></FIELD><FIELD attrname="PERCEPCION_IB_TASA" fieldtype="r8" required="true"><PARAM Name="ORIGIN" Value="PERCEPCION_IB_TASA" Roundtrip="True"/></FIELD><FIELD attrname="PERCEPCION_IB_IMPORTE" fieldtype="r8" required="true"><PARAM Name="ORIGIN" Value="PERCEPCION_IB_IMPORTE" Roundtrip="True"/></FIELD><FIELD attrname="PERCIBE_IB" fieldtype="string" required="true" SUBTYPE="FixedChar" WIDTH="1"><PARAM Name="ORIGIN" Value="PERCIBE_IB" Roundtrip="True"/></FIELD><FIELD attrname="PERCEPCION_IB_BASEIMPONIBLE" fieldtype="r8" required="true"><PARAM Name="ORIGIN" Value="PERCEPCION_IB_BASEIMPONIBLE" Roundtrip="True"/></FIELD><FIELD attrname="RENGLONES" fieldtype="i2" required="true"><PARAM Name="ORIGIN" Value="RENGLONES" Roundtrip="True"/></FIELD><FIELD attrname="FECHA_HORA" fieldtype="SQLdateTime"><PARAM Name="ORIGIN" Value="FECHA_HORA" Roundtrip="True"/></FIELD><FIELD attrname="NOTAPEDIDO_ID" fieldtype="i4"><PARAM Name="ORIGIN" Value="NOTAPEDIDO_ID" Roundtrip="True"/></FIELD><FIELD attrname="NOTAPEDIDO_NROCPBTE" fieldtype="string" WIDTH="13"><PARAM Name="ORIGIN" Value="NOTAPEDIDO_NROCPBTE" Roundtrip="True"/></FIELD><FIELD attrname="ID_FC_CLON" fieldtype="i4"><PARAM Name="ORIGIN" Value="ID_FC_CLON" Roundtrip="True"/></FIELD><FIELD attrname="PRESUPUESTO_ID" fieldtype="i4"><PARAM Name="ORIGIN" Value="PRESUPUESTO_ID" Roundtrip="True"/></FIELD><FIELD attrname="PRESUPUESTO_NROCPBTE" fieldtype="string" WIDTH="13"><PARAM Name="ORIGIN" Value="PRESUPUESTO_NROCPBTE" Roundtrip="True"/></FIELD><FIELD attrname="MONEDA_CPBTE" fieldtype="i4"><PARAM Name="ORIGIN" Value="MONEDA_CPBTE" Roundtrip="True"/></FIELD><FIELD attrname="MONEDA_CPBTE_COTIZACION" fieldtype="r8"><PARAM Name="ORIGIN" Value="MONEDA_CPBTE_COTIZACION" Roundtrip="True"/></FIELD><FIELD attrname="POR_CTA_Y_ORDEN" fieldtype="string" required="true" SUBTYPE="FixedChar" WIDTH="1"><PARAM Name="ORIGIN" Value="POR_CTA_Y_ORDEN" Roundtrip="True"/></FIELD><FIELD attrname="PROVEEDOR" fieldtype="string" WIDTH="6"><PARAM Name="ORIGIN" Value="PROVEEDOR" Roundtrip="True"/></FIELD><FIELD attrname="TIPO_VTA" fieldtype="string" SUBTYPE="FixedChar" WIDTH="1"><PARAM Name="ORIGIN" Value="TIPO_VTA" Roundtrip="True"/></FIELD><FIELD attrname="ID_RECEPCION_GTIA" fieldtype="i4"><PARAM Name="ORIGIN" Value="ID_RECEPCION_GTIA" Roundtrip="True"/></FIELD><FIELD attrname="JURIDICION" fieldtype="i4"><PARAM Name="ORIGIN" Value="JURIDICION" Roundtrip="True"/></FIELD><FIELD attrname="JURIDICION_LOCALIDAD" fieldtype="i4"><PARAM Name="ORIGIN" Value="JURIDICION_LOCALIDAD" Roundtrip="True"/></FIELD><FIELD attrname="CON_GTIA_EXTENDIDA" fieldtype="string" required="true" SUBTYPE="FixedChar" WIDTH="1"><PARAM Name="ORIGIN" Value="CON_GTIA_EXTENDIDA" Roundtrip="True"/></FIELD><FIELD attrname="MESES_DE_GARANTIA" fieldtype="i4" required="true"><PARAM Name="ORIGIN" Value="MESES_DE_GARANTIA" Roundtrip="True"/></FIELD><FIELD attrname="POLIZA" fieldtype="string" WIDTH="20"><PARAM Name="ORIGIN" Value="POLIZA" Roundtrip="True"/></FIELD><FIELD attrname="VALOR_ASEGURADO" fieldtype="r8"><PARAM Name="ORIGIN" Value="VALOR_ASEGURADO" Roundtrip="True"/></FIELD><FIELD attrname="ABONO_PERIODO" fieldtype="string" WIDTH="6"><PARAM Name="ORIGIN" Value="ABONO_PERIODO" Roundtrip="True"/></FIELD><FIELD attrname="NUMERO_OPERACION" fieldtype="string" WIDTH="8"><PARAM Name="ORIGIN" Value="NUMERO_OPERACION" Roundtrip="True"/></FIELD><FIELD attrname="SALDO_ACTUAL_CC" fieldtype="r8"><PARAM Name="ORIGIN" Value="SALDO_ACTUAL_CC" Roundtrip="True"/></FIELD><FIELD attrname="ID_NOTA_CAMBIO" fieldtype="i4"><PARAM Name="ORIGIN" Value="ID_NOTA_CAMBIO" Roundtrip="True"/></FIELD><FIELD attrname="CAE" fieldtype="string" required="true" WIDTH="50"><PARAM Name="ORIGIN" Value="CAE" Roundtrip="True"/></FIELD><FIELD attrname="CAE_VENCIMIENTO" fieldtype="SQLdateTime"><PARAM Name="ORIGIN" Value="CAE_VENCIMIENTO" Roundtrip="True"/></FIELD><FIELD attrname="FACTURA_ELECTRONICA" fieldtype="string" required="true" SUBTYPE="FixedChar" WIDTH="1"><PARAM Name="ORIGIN" Value="FACTURA_ELECTRONICA" Roundtrip="True"/></FIELD><FIELD attrname="CANT_BULTOS" fieldtype="i4" required="true"><PARAM Name="ORIGIN" Value="CANT_BULTOS" Roundtrip="True"/></FIELD><FIELD attrname="CUOTAS_CC" fieldtype="i4" required="true"><PARAM Name="ORIGIN" Value="CUOTAS_CC" Roundtrip="True"/></FIELD><FIELD attrname="INTERVALO_CUOTA" fieldtype="i4" required="true"><PARAM Name="ORIGIN" Value="INTERVALO_CUOTA" Roundtrip="True"/></FIELD><FIELD attrname="ID_GARANTE" fieldtype="i4"><PARAM Name="ORIGIN" Value="ID_GARANTE" Roundtrip="True"/></FIELD><FIELD attrname="PAGO_A_CTA" fieldtype="r8" required="true"><PARAM Name="ORIGIN" Value="PAGO_A_CTA" Roundtrip="True"/></FIELD><FIELD attrname="ID_FC_CON_ADEL" fieldtype="i4" required="true"><PARAM Name="ORIGIN" Value="ID_FC_CON_ADEL" Roundtrip="True"/></FIELD><FIELD attrname="PRIMER_VTO" fieldtype="SQLdateTime"><PARAM Name="ORIGIN" Value="PRIMER_VTO" Roundtrip="True"/></FIELD><FIELD attrname="ANTICIPO_VTO" fieldtype="SQLdateTime"><PARAM Name="ORIGIN" Value="ANTICIPO_VTO" Roundtrip="True"/></FIELD><FIELD attrname="CENTRO_COSTO" fieldtype="i4" required="true"><PARAM Name="ORIGIN" Value="CENTRO_COSTO" Roundtrip="True"/></FIELD><FIELD attrname="ID_PEDIDO_MORPHI" fieldtype="i4"><PARAM Name="ORIGIN" Value="ID_PEDIDO_MORPHI" Roundtrip="True"/></FIELD><FIELD attrname="ID_PAIS" fieldtype="i2"><PARAM Name="ORIGIN" Value="ID_PAIS" Roundtrip="True"/></FIELD><FIELD attrname="CUIT_PAIS" fieldtype="string" WIDTH="13"><PARAM Name="ORIGIN" Value="CUIT_PAIS" Roundtrip="True"/></FIELD><FIELD attrname="DOC_ADUANERO" fieldtype="string" WIDTH="15"><PARAM Name="ORIGIN" Value="DOC_ADUANERO" Roundtrip="True"/></FIELD><FIELD attrname="FECHA_CARGA" fieldtype="SQLdateTime"><PARAM Name="ORIGIN" Value="FECHA_CARGA" Roundtrip="True"/></FIELD><FIELD attrname="NRO_INTERNO" fieldtype="string" WIDTH="20"><PARAM Name="ORIGIN" Value="NRO_INTERNO" Roundtrip="True"/></FIELD><FIELD attrname="FOB_TOTAL" fieldtype="r8" required="true"><PARAM Name="ORIGIN" Value="FOB_TOTAL" Roundtrip="True"/></FIELD><FIELD attrname="NOTAS" fieldtype="string" WIDTH="300"><PARAM Name="ORIGIN" Value="NOTAS" Roundtrip="True"/></FIELD><FIELD attrname="DESTINO_DOCUMENTO" fieldtype="string" WIDTH="5"><PARAM Name="ORIGIN" Value="DESTINO_DOCUMENTO" Roundtrip="True"/></FIELD><FIELD attrname="PERMISO_EMBARQUE" fieldtype="string" WIDTH="100"><PARAM Name="ORIGIN" Value="PERMISO_EMBARQUE" Roundtrip="True"/></FIELD><FIELD attrname="INCOTERMS" fieldtype="string" WIDTH="5"><PARAM Name="ORIGIN" Value="INCOTERMS" Roundtrip="True"/></FIELD><FIELD attrname="CBU" fieldtype="string" WIDTH="22"><PARAM Name="ORIGIN" Value="CBU" Roundtrip="True"/></FIELD><FIELD attrname="ASOCIADO_ID_CPBTE" fieldtype="i4" required="true"><PARAM Name="ORIGIN" Value="ASOCIADO_ID_CPBTE" Roundtrip="True"/></FIELD><FIELD attrname="ASOCIADO_TIPO" fieldtype="i4"><PARAM Name="ORIGIN" Value="ASOCIADO_TIPO" Roundtrip="True"/></FIELD><FIELD attrname="ASOCIADO_PTOVTA" fieldtype="i4"><PARAM Name="ORIGIN" Value="ASOCIADO_PTOVTA" Roundtrip="True"/></FIELD><FIELD attrname="ASOCIADO_NRO" fieldtype="r8" required="true"><PARAM Name="ORIGIN" Value="ASOCIADO_NRO" Roundtrip="True"/></FIELD><FIELD attrname="ASOCIADO_CPTEFCH" fieldtype="string" WIDTH="8"><PARAM Name="ORIGIN" Value="ASOCIADO_CPTEFCH" Roundtrip="True"/></FIELD><FIELD attrname="INF_X" fieldtype="string" required="true" SUBTYPE="FixedChar" WIDTH="1"><PARAM Name="ORIGIN" Value="INF_X" Roundtrip="True"/></FIELD><FIELD attrname="TIPO_OPERACION_EXPO" fieldtype="string" SUBTYPE="FixedChar" WIDTH="1"><PARAM Name="ORIGIN" Value="TIPO_OPERACION_EXPO" Roundtrip="True"/></FIELD><FIELD attrname="MEDIO_TRANSPORTE_EXPO" fieldtype="string" WIDTH="20"><PARAM Name="ORIGIN" Value="MEDIO_TRANSPORTE_EXPO" Roundtrip="True"/></FIELD><FIELD attrname="ID_ADUANA" fieldtype="i4"><PARAM Name="ORIGIN" Value="ID_ADUANA" Roundtrip="True"/></FIELD><FIELD attrname="REFERENCIA_EXPO" fieldtype="string" WIDTH="30"><PARAM Name="ORIGIN" Value="REFERENCIA_EXPO" Roundtrip="True"/></FIELD><FIELD attrname="CAMBIO_EXPO" fieldtype="r8"><PARAM Name="ORIGIN" Value="CAMBIO_EXPO" Roundtrip="True"/></FIELD><FIELD attrname="VUELTO" fieldtype="r8" required="true"><PARAM Name="ORIGIN" Value="VUELTO" Roundtrip="True"/></FIELD><FIELD attrname="ID_TRANSPORTE" fieldtype="i4"><PARAM Name="ORIGIN" Value="ID_TRANSPORTE" Roundtrip="True"/></FIELD><FIELD attrname="ID_DESTINO" fieldtype="i4"><PARAM Name="ORIGIN" Value="ID_DESTINO" Roundtrip="True"/></FIELD><FIELD attrname="HONORARIOS" fieldtype="r8" required="true"><PARAM Name="ORIGIN" Value="HONORARIOS" Roundtrip="True"/></FIELD><FIELD attrname="HONORARIOS_PROCENTAJ" fieldtype="r8" required="true"><PARAM Name="ORIGIN" Value="HONORARIOS_PROCENTAJ" Roundtrip="True"/></FIELD><FIELD attrname="DEDUCE_GASTOS" fieldtype="string" SUBTYPE="FixedChar" WIDTH="1"><PARAM Name="ORIGIN" Value="DEDUCE_GASTOS" Roundtrip="True"/></FIELD><FIELD attrname="CON_CAEA" fieldtype="string" required="true" SUBTYPE="FixedChar" WIDTH="1"><PARAM Name="ORIGIN" Value="CON_CAEA" Roundtrip="True"/></FIELD><FIELD attrname="CAEA_INFORMADO" fieldtype="string" required="true" SUBTYPE="FixedChar" WIDTH="1"><PARAM Name="ORIGIN" Value="CAEA_INFORMADO" Roundtrip="True"/></FIELD><FIELD attrname="FACTURA_DE_ANTICIPO" fieldtype="string" required="true" SUBTYPE="FixedChar" WIDTH="1"><PARAM Name="ORIGIN" Value="FACTURA_DE_ANTICIPO" Roundtrip="True"/></FIELD><FIELD attrname="QRIMAGE" fieldtype="bin.hex" SUBTYPE="Binary"><PARAM Name="ORIGIN" Value="QRIMAGE" Roundtrip="True"/></FIELD><FIELD attrname="CONDICIONPEDIDO" fieldtype="i4" required="true"><PARAM Name="ORIGIN" Value="CONDICIONPEDIDO" Roundtrip="True"/></FIELD><FIELD attrname="KEY_PLANER" fieldtype="string" WIDTH="40"><PARAM Name="ORIGIN" Value="KEY_PLANER" Roundtrip="True"/></FIELD><FIELD attrname="MUESTRACONDVENTA" fieldtype="string" readonly="true" WIDTH="20"><PARAM Name="PROVFLAGS" Value="0" Type="i4" Roundtrip="True"/><PARAM Name="ORIGIN" Value="DETALLE" Roundtrip="True"/></FIELD><FIELD attrname="MUESTRADEPOSITO" fieldtype="string" readonly="true" WIDTH="25"><PARAM Name="PROVFLAGS" Value="0" Type="i4" Roundtrip="True"/><PARAM Name="ORIGIN" Value="NOMBRE" Roundtrip="True"/></FIELD><FIELD attrname="MUESTRASUCURSAL" fieldtype="string" readonly="true" WIDTH="35"><PARAM Name="PROVFLAGS" Value="0" Type="i4" Roundtrip="True"/><PARAM Name="ORIGIN" Value="DETALLE" Roundtrip="True"/></FIELD><FIELD attrname="MUESTRALDR" fieldtype="string" readonly="true" WIDTH="35"><PARAM Name="PROVFLAGS" Value="0" Type="i4" Roundtrip="True"/><PARAM Name="ORIGIN" Value="NOMBRE" Roundtrip="True"/></FIELD><FIELD attrname="MUESTRADIRECCIONLDR" fieldtype="string" readonly="true" WIDTH="35"><PARAM Name="PROVFLAGS" Value="0" Type="i4" Roundtrip="True"/><PARAM Name="ORIGIN" Value="DIRECCION" Roundtrip="True"/></FIELD><FIELD attrname="MUESTRAIVA" fieldtype="string" readonly="true" WIDTH="15"><PARAM Name="PROVFLAGS" Value="0" Type="i4" Roundtrip="True"/><PARAM Name="ORIGIN" Value="DETALLE" Roundtrip="True"/></FIELD><FIELD attrname="MUESTRACOMPROBANTE" fieldtype="string" readonly="true" WIDTH="15"><PARAM Name="PROVFLAGS" Value="0" Type="i4" Roundtrip="True"/><PARAM Name="ORIGIN" Value="DENOMINACION" Roundtrip="True"/></FIELD><FIELD attrname="ID_TIPOCOMPROBANTE" fieldtype="i4" readonly="true"><PARAM Name="PROVFLAGS" Value="0" Type="i4" Roundtrip="True"/><PARAM Name="ORIGIN" Value="ID_COMPROBANTE" Roundtrip="True"/></FIELD><FIELD attrname="MUESTRAVENDEDOR" fieldtype="string" readonly="true" WIDTH="50"><PARAM Name="PROVFLAGS" Value="0" Type="i4" Roundtrip="True"/><PARAM Name="ORIGIN" Value="NOMBRE" Roundtrip="True"/></FIELD><FIELD attrname="MUESTRAPROVEEDOR" fieldtype="string" readonly="true" WIDTH="35"><PARAM Name="PROVFLAGS" Value="0" Type="i4" Roundtrip="True"/><PARAM Name="ORIGIN" Value="NOMBRE" Roundtrip="True"/></FIELD><FIELD attrname="MUESTRAMONEDACPBTE" fieldtype="string" readonly="true" WIDTH="15"><PARAM Name="PROVFLAGS" Value="0" Type="i4" Roundtrip="True"/><PARAM Name="ORIGIN" Value="MONEDA" Roundtrip="True"/></FIELD><FIELD attrname="MUESTRASIGNOMONEDACPBTE" fieldtype="string" readonly="true" WIDTH="5"><PARAM Name="PROVFLAGS" Value="0" Type="i4" Roundtrip="True"/><PARAM Name="ORIGIN" Value="SIGNO" Roundtrip="True"/></FIELD><FIELD attrname="MUESTRAESFRANQUICIA" fieldtype="string" readonly="true" SUBTYPE="FixedChar" WIDTH="1"><PARAM Name="PROVFLAGS" Value="0" Type="i4" Roundtrip="True"/><PARAM Name="ORIGIN" Value="FRANQUICIA" Roundtrip="True"/></FIELD><FIELD attrname="MUESTRACOORPORATIVO" fieldtype="string" readonly="true" WIDTH="6"><PARAM Name="PROVFLAGS" Value="0" Type="i4" Roundtrip="True"/><PARAM Name="ORIGIN" Value="CODIGO_COORPORATIVO" Roundtrip="True"/></FIELD><FIELD attrname="MUESTRACODIGOAFIP" fieldtype="string" readonly="true" WIDTH="3"><PARAM Name="PROVFLAGS" Value="0" Type="i4" Roundtrip="True"/><PARAM Name="ORIGIN" Value="CODIGO_AFIP" Roundtrip="True"/></FIELD><FIELD attrname="MUESTRAZONA" fieldtype="string" readonly="true" WIDTH="25"><PARAM Name="PROVFLAGS" Value="0" Type="i4" Roundtrip="True"/><PARAM Name="ORIGIN" Value="DETALLE" Roundtrip="True"/></FIELD><FIELD attrname="MUESTRAOBSCLIENTE1" fieldtype="string" readonly="true" WIDTH="60"><PARAM Name="PROVFLAGS" Value="0" Type="i4" Roundtrip="True"/><PARAM Name="ORIGIN" Value="OBSERVACIONES1" Roundtrip="True"/></FIELD><FIELD attrname="MUESTRAOBSCLIENTE2" fieldtype="string" readonly="true" WIDTH="60"><PARAM Name="PROVFLAGS" Value="0" Type="i4" Roundtrip="True"/><PARAM Name="ORIGIN" Value="OBSERVACIONES2" Roundtrip="True"/></FIELD><FIELD attrname="MUESTRAACOPIO" fieldtype="i4" readonly="true"><PARAM Name="PROVFLAGS" Value="0" Type="i4" Roundtrip="True"/><PARAM Name="ORIGIN" Value="ID" Roundtrip="True"/></FIELD><FIELD attrname="MUESTRANOMBRECOMPLETO" fieldtype="string" readonly="true" WIDTH="100"><PARAM Name="PROVFLAGS" Value="0" Type="i4" Roundtrip="True"/><PARAM Name="ORIGIN" Value="NOMBRE_COMPLETO" Roundtrip="True"/></FIELD><FIELD attrname="MUESTRAIDABONO" fieldtype="i4" readonly="true"><PARAM Name="PROVFLAGS" Value="0" Type="i4" Roundtrip="True"/><PARAM Name="ORIGIN" Value="ID" Roundtrip="True"/></FIELD><FIELD attrname="MUESTRANROABONO" fieldtype="string" readonly="true" WIDTH="8"><PARAM Name="PROVFLAGS" Value="0" Type="i4" Roundtrip="True"/><PARAM Name="ORIGIN" Value="NUMERO" Roundtrip="True"/></FIELD><FIELD attrname="ENVIAR_CPTE_MAIL" fieldtype="string" readonly="true" SUBTYPE="FixedChar" WIDTH="1"><PARAM Name="PROVFLAGS" Value="0" Type="i4" Roundtrip="True"/><PARAM Name="ORIGIN" Value="ENVIAR_CPTE_MAIL" Roundtrip="True"/></FIELD><FIELD attrname="MUESTRAUSACHE" fieldtype="string" readonly="true" SUBTYPE="FixedChar" WIDTH="1"><PARAM Name="PROVFLAGS" Value="0" Type="i4" Roundtrip="True"/><PARAM Name="ORIGIN" Value="CHEQUES" Roundtrip="True"/></FIELD><FIELD attrname="MUESTRATRANSPORTE" fieldtype="string" readonly="true" WIDTH="50"><PARAM Name="PROVFLAGS" Value="0" Type="i4" Roundtrip="True"/><PARAM Name="ORIGIN" Value="NOMBRE" Roundtrip="True"/></FIELD><FIELD attrname="MUESTRAID_NC" fieldtype="i4"><PARAM Name="PROVFLAGS" Value="0" Type="i4" Roundtrip="True"/><PARAM Name="ORIGIN" Value="ID_FC" Roundtrip="True"/></FIELD><FIELD attrname="MUESTRANRONC" fieldtype="string" WIDTH="13"><PARAM Name="PROVFLAGS" Value="0" Type="i4" Roundtrip="True"/><PARAM Name="ORIGIN" Value="NROCPBTE" Roundtrip="True"/></FIELD><FIELD attrname="MUESTRATIPONC" fieldtype="string" WIDTH="2"><PARAM Name="PROVFLAGS" Value="0" Type="i4" Roundtrip="True"/><PARAM Name="ORIGIN" Value="TIPOCPBTE" Roundtrip="True"/></FIELD><FIELD attrname="MUESTRACLASENC" fieldtype="string" WIDTH="2"><PARAM Name="PROVFLAGS" Value="0" Type="i4" Roundtrip="True"/><PARAM Name="ORIGIN" Value="CLASECPBTE" Roundtrip="True"/></FIELD><FIELD attrname="LOTEAFIP" fieldtype="string" WIDTH="8"><PARAM Name="PROVFLAGS" Value="0" Type="i4" Roundtrip="True"/><PARAM Name="ORIGIN" Value="LOTEAFIP" Roundtrip="True"/></FIELD><FIELD attrname="CODIGO_ACTIVIDAD" fieldtype="string" required="true" WIDTH="10"><PARAM Name="ORIGIN" Value="CODIGO_ACTIVIDAD" Roundtrip="True"/></FIELD></FIELDS><PARAMS PRIMARY_KEY="1"/></METADATA><ROWDATA><ROW ID_FC="228518" TIPOCPBTE="TK" CLASECPBTE="TF" CODIGO="000098" NROCPBTE="B000500000604" LETRAFAC="B" SUCFAC="0005" NUMEROFAC="00000604" NOMBRE="CONSUMIDOR FINAL" RAZONSOCIAL="CONSUMIDOR FINAL" DIRECCION="" CPOSTAL="" LOCALIDAD="" TIPOIVA="3" CUIT="" LISTAPRECIO="1" FECHAVTA="20230211" FECHAVTO="20230211" FECHA_FISCAL="20230211" CONDICIONVTA="0" ANULADO="N" NRORTO="" N_OPERACION2="0" NETOGRAV1="53719.01" NETOGRAV2="53719.01" NETONOGRAV1="0" NETONOGRAV2="0" DSTO="0" DSTOIMPORTE="0" NETOEXEN1="0" NETOEXEN2="0" TOTAL="65000" DEBE="65000" IMPRESO="N" CPTE_MANUAL="N" SUCURSAL="1" ZONA="0" LDR="0" DEPOSITO="1" CALCULA_SOBRETASA="N" DESGLOZAIVA="N" NROENTREGA="1" INGRESA_A_CTACTE="N" INGRESA_LIBRO_IVA="S" REDUCIDA="N" COMSIONVENDEDOR="10" LIQUIDADA="N" VENDEDOR="000001" USUARIO="master" NC_CONTADO="N" CAJA_POR_DEFECTO="101" VALORES_RECIBIDOS="0" PERCEPCION_IB_TASA="8" PERCEPCION_IB_IMPORTE="0" PERCIBE_IB="N" PERCEPCION_IB_BASEIMPONIBLE="0" RENGLONES="1" FECHA_HORA="20230211T13:27:21052" NOTAPEDIDO_ID="0" MONEDA_CPBTE="-1" MONEDA_CPBTE_COTIZACION="1" POR_CTA_Y_ORDEN="N" PROVEEDOR="" TIPO_VTA="M" CON_GTIA_EXTENDIDA="N" MESES_DE_GARANTIA="0" VALOR_ASEGURADO="0" NUMERO_OPERACION="-1" SALDO_ACTUAL_CC="11136.24000000001" CAE="0" FACTURA_ELECTRONICA="S" CANT_BULTOS="1" CUOTAS_CC="1" INTERVALO_CUOTA="30" ID_GARANTE="0" PAGO_A_CTA="0" ID_FC_CON_ADEL="-1" CENTRO_COSTO="-1" ID_PEDIDO_MORPHI="-1" FOB_TOTAL="0" NOTAS="" CBU="1234567890123456789012" ASOCIADO_ID_CPBTE="-1" ASOCIADO_TIPO="0" ASOCIADO_PTOVTA="0" ASOCIADO_NRO="0" ASOCIADO_CPTEFCH="00000000" INF_X="N" VUELTO="0" HONORARIOS="0" HONORARIOS_PROCENTAJ="0" DEDUCE_GASTOS="N" CON_CAEA="N" CAEA_INFORMADO="N" FACTURA_DE_ANTICIPO="N" CONDICIONPEDIDO="-1" MUESTRADEPOSITO="J B JUSTO." MUESTRASUCURSAL="Casa Central" MUESTRALDR="CONSUMIDOR FINAL" MUESTRAIVA="C.FINAL" MUESTRACOMPROBANTE="Tik Fac B (E)" ID_TIPOCOMPROBANTE="433" MUESTRAVENDEDOR="CIANO EDUARDO" MUESTRACODIGOAFIP="006" MUESTRANOMBRECOMPLETO="CONSUMIDOR FINAL" ENVIAR_CPTE_MAIL="N" MUESTRAUSACHE="S" CODIGO_ACTIVIDAD="**********"/></ROWDATA></DATAPACKET>